{
	"info": {
		"_postman_id": "28afdad0-0681-42d0-b65e-474b36b2eccf",
		"name": "Ricardo",
		"schema": "https://schema.getpostman.com/json/collection/v2.1.0/collection.json",
		"_exporter_id": "650489"
	},
	"item": [
		{
			"name": "Ingredientes",
			"item": [
				{
					"name": "listar todos os ingredientes",
					"request": {
						"method": "GET",
						"header": [],
						"url": {
							"raw": "http://localhost:8080/api/v1/ingredientes",
							"protocol": "http",
							"host": [
								"localhost"
							],
							"port": "8080",
							"path": [
								"api",
								"v1",
								"ingredientes"
							]
						}
					},
					"response": []
				}
			]
		},
		{
			"name": "Usuarios",
			"item": [
				{
					"name": "listar todos os usuários",
					"request": {
						"method": "GET",
						"header": [],
						"url": {
							"raw": "http://localhost:8080/api/v1/usuarios",
							"protocol": "http",
							"host": [
								"localhost"
							],
							"port": "8080",
							"path": [
								"api",
								"v1",
								"usuarios"
							]
						}
					},
					"response": []
				},
				{
					"name": "buscar usuário por id",
					"request": {
						"method": "GET",
						"header": [],
						"url": {
							"raw": "http://localhost:8080/api/v1/usuarios/:id",
							"protocol": "http",
							"host": [
								"localhost"
							],
							"port": "8080",
							"path": [
								"api",
								"v1",
								"usuarios",
								":id"
							],
							"variable": [
								{
									"key": "id",
									"value": "1"
								}
							]
						}
					},
					"response": []
				}
			]
		},
		{
			"name": "Refeições",
			"item": [
				{
					"name": "listar todas as refeições de uma dieta",
					"request": {
						"method": "GET",
						"header": [],
						"url": {
							"raw": "http://localhost:8080/api/v1/dietas/:id/refeicoes",
							"protocol": "http",
							"host": [
								"localhost"
							],
							"port": "8080",
							"path": [
								"api",
								"v1",
								"dietas",
								":id",
								"refeicoes"
							],
							"variable": [
								{
									"key": "id",
									"value": "1"
								}
							]
						}
					},
					"response": []
				},
				{
					"name": "listar refeições da dieta por data",
					"request": {
						"method": "GET",
						"header": [],
						"url": {
							"raw": "http://localhost:8080/api/v1/dietas/:id/refeicoes",
							"protocol": "http",
							"host": [
								"localhost"
							],
							"port": "8080",
							"path": [
								"api",
								"v1",
								"dietas",
								":id",
								"refeicoes"
							],
							"query": [
								{
									"key": "data",
									"value": "2024-11-05",
									"disabled": true
								}
							],
							"variable": [
								{
									"key": "id",
									"value": "2"
								}
							]
						}
					},
					"response": []
				}
			]
		},
		{
			"name": "Dietas",
			"item": [
				{
					"name": "listar todas as dietas",
					"request": {
						"method": "GET",
						"header": [],
						"url": {
							"raw": "http://localhost:8080/api/v1/dietas",
							"protocol": "http",
							"host": [
								"localhost"
							],
							"port": "8080",
							"path": [
								"api",
								"v1",
								"dietas"
							]
						}
					},
					"response": []
				}
			]
		}
	]
}